cpp_diann/app.py
cpp_diann/run.py
cpp_diann-0.1.0.dist-info/METADATA
cpp_diann-0.1.0.dist-info/WHEEL
cpp_diann-0.1.0.dist-info/entry_points.txt
cpp_diann-0.1.0.dist-info/top_level.txt
cpp_diann-0.1.0.dist-info/RECORD
